[
  {
    "block_number": 3,
    "block_id": "9f9ce2..24e1de",
    "timestamp": "1900-12-13T19:33:17.830000"
  },
  {
    "block_number": 4,
    "block_id": "5b04cb..bd8a4a",
    "timestamp": "1900-12-13T19:33:28.345000"
  },
  {
    "block_number": 5,
    "block_id": "77a040..af101b",
    "timestamp": "1900-12-13T19:33:34.393000"
  },
  {
    "block_number": 8,
    "block_id": "ac8b2b..a1bd34",
    "timestamp": "1900-12-13T19:33:40.054000"
  },
  {
    "block_number": 12,
    "block_id": "326d40..d48cbf",
    "timestamp": "1900-12-13T19:33:55.816000"
  },
  {
    "block_number": 13,
    "block_id": "7f4bb5..911e3f",
    "timestamp": "1900-12-13T19:34:03.906000"
  },
  {
    "block_number": 23,
    "block_id": "b9fa2c..6a3623",
    "timestamp": "1900-12-13T19:34:13.401000"
  },
  {
    "block_number": 25,
    "block_id": "b1e692..da9e71",
    "timestamp": "1900-12-13T19:34:16.657000"
  },
  {
    "block_number": 26,
    "block_id": "732624..5938ae",
    "timestamp": "1900-12-13T19:34:17.148000"
  },
  {
    "block_number": 35,
    "block_id": "a38f02..2d22a6",
    "timestamp": "1900-12-13T19:34:25.631000"
  },
  {
    "block_number": 37,
    "block_id": "09fac6..16f84c",
    "timestamp": "1900-12-13T19:34:31.356000"
  },
  {
    "block_number": 40,
    "block_id": "0cbf4c..d46ba4",
    "timestamp": "1900-12-13T19:34:36.731000"
  }
]